setup.py
salure_helpers/maxxton/__init__.py
salure_helpers/maxxton/maxxton.py
salure_helpers_maxxton.egg-info/PKG-INFO
salure_helpers_maxxton.egg-info/SOURCES.txt
salure_helpers_maxxton.egg-info/dependency_links.txt
salure_helpers_maxxton.egg-info/not-zip-safe
salure_helpers_maxxton.egg-info/requires.txt
salure_helpers_maxxton.egg-info/top_level.txt